{
  "A.J. Lawson": 0.7619,
  "AJ Green": 0.5,
  "AJ Johnson": 0.7692,
  "Aaron Gordon": 0.7037,
  "Aaron Holiday": 0.6324,
  "Aaron Nesmith": 0.7317,
  "Aaron Wiggins": 0.646,
  "Ace Bailey": 0.6308,
  "Adam Flagler": 0.8966,
  "Adem Bona": 0.6914,
  "Ajay Mitchell": 0.6951,
  "Al Horford": 0.5914,
  "Alec Burks": 0.7045,
  "Alex Caruso": 0.5714,
  "Alex Ducas": 0.9375,
  "Alex Len": 0.7949,
  "Alex Reese": 0.8,
  "Alex Sarr": 0.5818,
  "Alperen Sengun": 0.6809,
  "Amen Thompson": 0.5674,
  "Amir Coffey": 0.6418,
  "Andre Drummond": 0.6849,
  "Andre Jackson Jr.": 0.5763,
  "Andrew Nembhard": 0.6034,
  "Andrew Wiggins": 0.626,
  "Anfernee Simons": 0.6525,
  "Anthony Black": 0.6074,
  "Anthony Davis": 0.7424,
  "Anthony Edwards": 0.6194,
  "Anthony Gill": 0.5957,
  "Antonio Reeves": 0.8205,
  "Ariel Hukporti": 0.8095,
  "Ausar Thompson": 0.656,
  "Austin Reaves": 0.6356,
  "Ayo Dosunmu": 0.5794,
  "Bam Adebayo": 0.5616,
  "Baylor Scheierman": 0.7451,
  "Ben Saraf": 0.75,
  "Ben Sheppard": 0.7245,
  "Ben Simmons": 0.7391,
  "Bennedict Mathurin": 0.5391,
  "Bilal Coulibaly": 0.6111,
  "Bismack Biyombo": 0.6818,
  "Blake Wesley": 0.7193,
  "Bobby Portis": 0.6154,
  "Bogdan Bogdanovi\u0107": 0.7143,
  "Bol Bol": 0.7097,
  "Bones Hyland": 0.675,
  "Bradley Beal": 0.6852,
  "Branden Carlson": 0.7692,
  "Brandin Podziemski": 0.6232,
  "Brandon Boston": 0.5946,
  "Brandon Clarke": 0.5833,
  "Brandon Ingram": 0.5444,
  "Brandon Miller": 0.6279,
  "Brandon Williams": 0.6324,
  "Brice Sensabaugh": 0.592,
  "Bronny James": 0.75,
  "Brook Lopez": 0.6364,
  "Bruce Brown": 0.5941,
  "Bryce McGowens": 0.8571,
  "Bub Carrington": 0.5844,
  "Buddy Hield": 0.6981,
  "CJ McCollum": 0.7843,
  "Cade Cunningham": 0.6929,
  "Caleb Houstan": 0.8491,
  "Caleb Martin": 0.66,
  "Cam Spencer": 0.72,
  "Cam Thomas": 0.6731,
  "Cam Whitmore": 0.65,
  "Cameron Johnson": 0.6226,
  "Cameron Payne": 0.6081,
  "Caris LeVert": 0.6566,
  "Cason Wallace": 0.6569,
  "Cedric Coward": 0.75,
  "Charles Bassey": 0.5172,
  "Chet Holmgren": 0.6915,
  "Chris Boucher": 0.5652,
  "Chris Livingston": 0.8125,
  "Chris Paul": 0.5976,
  "Christian Braun": 0.5776,
  "Christian Koloko": 0.7419,
  "Clint Capela": 0.6267,
  "Coby White": 0.605,
  "Cody Martin": 0.6875,
  "Cody Williams": 0.6747,
  "Colby Jones": 0.8125,
  "Cole Anthony": 0.642,
  "Colin Castleton": 0.75,
  "Collin Gillespie": 0.7075,
  "Collin Murray-Boyles": 0.7838,
  "Collin Sexton": 0.6372,
  "Cooper Flagg": 0.6984,
  "Corey Kispert": 0.6556,
  "Cory Joseph": 0.8667,
  "Craig Porter Jr.": 0.8043,
  "D'Angelo Russell": 0.6286,
  "DaQuan Jeffries": 0.7857,
  "Dalano Banton": 0.7258,
  "Dalen Terry": 0.5441,
  "Dalton Knecht": 0.7073,
  "Damian Lillard": 0.6981,
  "Damion Baugh": 0.9,
  "Damion Lee": 0.75,
  "Daniel Gafford": 0.6275,
  "Daniss Jenkins": 0.7727,
  "Danny Wolf": 0.825,
  "Dant\u00e9 Exum": 0.9333,
  "Dario \u0160ari\u0107": 0.5455,
  "Dariq Whitehead": 0.9231,
  "Darius Garland": 0.614,
  "David Roddy": 0.75,
  "Davion Mitchell": 0.6232,
  "Day'Ron Sharpe": 0.6162,
  "De'Aaron Fox": 0.6484,
  "De'Andre Hunter": 0.57,
  "De'Anthony Melton": 0.6889,
  "DeAndre Jordan": 0.6667,
  "DeMar DeRozan": 0.5906,
  "Dean Wade": 0.6604,
  "Deandre Ayton": 0.5769,
  "Dejounte Murray": 0.7179,
  "Delon Wright": 0.8286,
  "Deni Avdija": 0.5373,
  "Dennis Schr\u00f6der": 0.6857,
  "Dereck Lively II": 0.6842,
  "Derik Queen": 0.6765,
  "Derrick Jones Jr.": 0.6667,
  "Derrick White": 0.6351,
  "Desmond Bane": 0.5479,
  "Devin Booker": 0.6519,
  "Devin Carter": 0.7111,
  "Devin Vassell": 0.632,
  "Dillon Brooks": 0.5669,
  "Dillon Jones": 0.8367,
  "Domantas Sabonis": 0.5595,
  "Dominick Barlow": 0.6667,
  "Donovan Clingan": 0.6357,
  "Donovan Mitchell": 0.6015,
  "Donte DiVincenzo": 0.6423,
  "Dorian Finney-Smith": 0.7037,
  "Doug McDermott": 0.725,
  "Drake Powell": 0.697,
  "Draymond Green": 0.6462,
  "Drew Eubanks": 0.6571,
  "Drew Peterson": 0.7368,
  "Dru Smith": 0.5484,
  "Duncan Robinson": 0.5903,
  "Duop Reath": 0.7317,
  "Dwight Powell": 0.6935,
  "Dylan Cardwell": 0.7,
  "Dylan Harper": 0.7097,
  "Dyson Daniels": 0.7055,
  "Elfrid Payton": 0.8947,
  "Enrique Freeman": 0.8125,
  "Eric Gordon": 0.7647,
  "Evan Mobley": 0.5349,
  "Franz Wagner": 0.5393,
  "Fred VanVleet": 0.7273,
  "GG Jackson": 0.75,
  "Gabe Vincent": 0.6667,
  "Garrett Temple": 0.9091,
  "Garrison Mathews": 0.8571,
  "Gary Harris": 0.72,
  "Gary Payton II": 0.6588,
  "Gary Trent Jr.": 0.6377,
  "Georges Niang": 0.527,
  "Giannis Antetokounmpo": 0.5361,
  "Goga Bitadze": 0.6364,
  "Gradey Dick": 0.6622,
  "Grant Williams": 0.6333,
  "Grayson Allen": 0.6542,
  "Guerschon Yabusele": 0.7468,
  "Gui Santos": 0.7195,
  "Harrison Barnes": 0.6327,
  "Haywood Highsmith": 0.6232,
  "Herbert Jones": 0.6667,
  "Hunter Tyson": 0.5333,
  "Immanuel Quickley": 0.7143,
  "Isaac Jones": 0.7143,
  "Isaac Okoro": 0.5929,
  "Isaiah Collier": 0.6991,
  "Isaiah Hartenstein": 0.6146,
  "Isaiah Jackson": 0.7037,
  "Isaiah Joe": 0.6325,
  "Isaiah Stewart": 0.6269,
  "Ivica Zubac": 0.5868,
  "JD Davison": 0.7,
  "JT Thor": 0.8,
  "Ja Morant": 0.6154,
  "Ja'Kobe Walter": 0.7191,
  "Jabari Smith Jr.": 0.6731,
  "Jabari Walker": 0.7627,
  "Jacob Toppin": 1.0,
  "Jaden Hardy": 0.5614,
  "Jaden Ivey": 0.6429,
  "Jaden McDaniels": 0.5878,
  "Jaden Springer": 0.7647,
  "Jae'Sean Tate": 0.617,
  "Jaime Jaquez Jr.": 0.6721,
  "Jake LaRavia": 0.6846,
  "Jakob Poeltl": 0.6146,
  "Jalen Brunson": 0.5821,
  "Jalen Duren": 0.5385,
  "Jalen Green": 0.6296,
  "Jalen Hood-Schifino": 0.7,
  "Jalen Johnson": 0.6176,
  "Jalen Pickett": 0.7368,
  "Jalen Smith": 0.5481,
  "Jalen Suggs": 0.6782,
  "Jalen Williams": 0.5361,
  "Jalen Wilson": 0.5625,
  "Jamal Cain": 0.697,
  "Jamal Murray": 0.6103,
  "Jamal Shead": 0.6966,
  "James Harden": 0.6479,
  "Jamison Battle": 0.6852,
  "Jarace Walker": 0.6296,
  "Jared Butler": 0.7091,
  "Jared McCain": 0.5714,
  "Jaren Jackson Jr.": 0.6812,
  "Jarred Vanderbilt": 0.5873,
  "Jarrett Allen": 0.5954,
  "Javonte Green": 0.622,
  "Jaxson Hayes": 0.6778,
  "Jay Huff": 0.6471,
  "Jaylen Brown": 0.6667,
  "Jaylen Clark": 0.7037,
  "Jaylen Martin": 0.9091,
  "Jaylen Wells": 0.6434,
  "Jaylin Williams": 0.597,
  "Jaylon Tyson": 0.6429,
  "Jayson Tatum": 0.6265,
  "Jeff Dowtin Jr.": 0.75,
  "Jeff Green": 0.5556,
  "Jerami Grant": 0.6042,
  "Jeremiah Fears": 0.6716,
  "Jeremiah Robinson-Earl": 0.6935,
  "Jeremy Sochan": 0.5667,
  "Jericho Sims": 0.619,
  "Jett Howard": 0.6032,
  "Jevon Carter": 0.6304,
  "Jimmy Butler III": 0.58,
  "Jock Landale": 0.6667,
  "Joel Embiid": 0.6538,
  "John Collins": 0.5743,
  "John Konchar": 0.6604,
  "Johnny Furphy": 0.75,
  "Johnny Juzang": 0.6102,
  "Jonas Valan\u010di\u016bnas": 0.6316,
  "Jonathan Isaac": 0.6795,
  "Jonathan Kuminga": 0.5733,
  "Jonathan Mogbo": 0.7241,
  "Jordan Clarkson": 0.6375,
  "Jordan Goodwin": 0.6061,
  "Jordan Hawkins": 0.6094,
  "Jordan McLaughlin": 0.725,
  "Jordan Miller": 0.6579,
  "Jordan Poole": 0.587,
  "Jordan Walsh": 0.7714,
  "Jose Alvarado": 0.6087,
  "Josh Giddey": 0.7227,
  "Josh Green": 0.6667,
  "Josh Hart": 0.6861,
  "Josh Minott": 0.7143,
  "Josh Okogie": 0.7286,
  "Jrue Holiday": 0.6577,
  "Julian Champagnie": 0.6456,
  "Julian Phillips": 0.6133,
  "Julian Strawther": 0.6316,
  "Julius Randle": 0.6364,
  "Justin Champagnie": 0.6889,
  "Justin Edwards": 0.6481,
  "Justin Minaya": 1.0,
  "Jusuf Nurki\u0107": 0.5652,
  "KJ Martin": 0.6842,
  "KJ Simpson": 0.8182,
  "Kai Jones": 0.7429,
  "Karl-Anthony Towns": 0.5845,
  "Karlo Matkovi\u0107": 0.6216,
  "Kawhi Leonard": 0.6327,
  "Keaton Wallace": 0.6667,
  "Keegan Murray": 0.617,
  "Kel'el Ware": 0.6379,
  "Keldon Johnson": 0.6242,
  "Kelly Olynyk": 0.6364,
  "Kelly Oubre Jr.": 0.6182,
  "Kenrich Williams": 0.6623,
  "Kentavious Caldwell-Pope": 0.6435,
  "Keon Ellis": 0.598,
  "Keon Johnson": 0.4865,
  "Keshad Johnson": 0.9091,
  "Kessler Edwards": 0.7059,
  "Kevin Durant": 0.6466,
  "Kevin Huerter": 0.6239,
  "Kevin Love": 0.6667,
  "Kevin Porter Jr.": 0.6887,
  "Kevon Looney": 0.76,
  "Keyonte George": 0.6,
  "Khris Middleton": 0.6867,
  "Klay Thompson": 0.6349,
  "Kobe Brown": 0.7209,
  "Kon Knueppel": 0.7067,
  "Kris Dunn": 0.5931,
  "Kris Murray": 0.69,
  "Kristaps Porzi\u0146\u0123is": 0.6757,
  "Kyle Anderson": 0.6167,
  "Kyle Filipowski": 0.6519,
  "Kyle Kuzma": 0.6452,
  "Kyle Lowry": 0.8667,
  "Kyrie Irving": 0.6889,
  "Kyshawn George": 0.6396,
  "LaMelo Ball": 0.6018,
  "Lamar Stevens": 0.9091,
  "Landry Shamet": 0.5595,
  "Larry Nance Jr.": 0.52,
  "Lauri Markkanen": 0.6024,
  "LeBron James": 0.6532,
  "Leonard Miller": 0.8125,
  "Lindy Waters III": 0.6809,
  "Lonnie Walker IV": 0.7857,
  "Lonzo Ball": 0.6038,
  "Luguentz Dort": 0.5985,
  "Luka Don\u010di\u0107": 0.5111,
  "Luka Garza": 0.6508,
  "Luke Kennard": 0.6852,
  "Luke Kornet": 0.6121,
  "Malaki Branham": 0.878,
  "Malcolm Brogdon": 0.4737,
  "Malik Beasley": 0.6494,
  "Malik Monk": 0.6,
  "MarJon Beauchamp": 0.8333,
  "Marcus Sasser": 0.569,
  "Marcus Smart": 0.618,
  "Mark Williams": 0.68,
  "Markelle Fultz": 0.75,
  "Markieff Morris": 0.9,
  "Marvin Bagley III": 0.5714,
  "Mason Plumlee": 0.7101,
  "Matas Buzelis": 0.5828,
  "Matisse Thybulle": 0.9167,
  "Max Christie": 0.5918,
  "Max Strus": 0.6852,
  "Maxi Kleber": 0.8966,
  "Maxime Raynaud": 0.6909,
  "Maxwell Lewis": 0.7727,
  "Micah Potter": 0.6579,
  "Michael Porter Jr.": 0.6389,
  "Mikal Bridges": 0.5732,
  "Mike Conley": 0.5714,
  "Miles Bridges": 0.5882,
  "Miles McBride": 0.6087,
  "Mitchell Robinson": 0.7164,
  "Mont\u00e9 Morris": 0.7,
  "Moritz Wagner": 0.48,
  "Moses Moody": 0.6429,
  "Mouhamed Gueye": 0.587,
  "Moussa Diabat\u00e9": 0.6615,
  "Myles Turner": 0.6889,
  "Naji Marshall": 0.6119,
  "Nate Williams": 0.8,
  "Naz Reid": 0.6579,
  "Neemias Queta": 0.6031,
  "Nic Claxton": 0.6615,
  "Nick Richards": 0.6833,
  "Nick Smith Jr.": 0.5636,
  "Nickeil Alexander-Walker": 0.5779,
  "Nicolas Batum": 0.6091,
  "Nikola Joki\u0107": 0.6462,
  "Nikola Jovi\u0107": 0.7073,
  "Nikola Vu\u010devi\u0107": 0.5882,
  "Nique Clifford": 0.7391,
  "Noah Clowney": 0.6509,
  "Nolan Traore": 0.8333,
  "Norman Powell": 0.6283,
  "OG Anunoby": 0.625,
  "Obi Toppin": 0.5488,
  "Ochai Agbaji": 0.7179,
  "Olivier-Maxence Prosper": 0.6129,
  "Onyeka Okongwu": 0.5714,
  "Oso Ighodaro": 0.6303,
  "Ousmane Dieng": 0.7,
  "P.J. Washington": 0.5701,
  "PJ Hall": 0.7143,
  "Pac\u00f4me Dadiet": 0.8462,
  "Paolo Banchero": 0.646,
  "Pascal Siakam": 0.5896,
  "Pat Connaughton": 0.5676,
  "Pat Spencer": 0.7647,
  "Patrick Baldwin Jr.": 0.8947,
  "Patrick Williams": 0.6593,
  "Patty Mills": 0.5833,
  "Paul George": 0.6986,
  "Paul Reed": 0.65,
  "Payton Pritchard": 0.6601,
  "Pelle Larsson": 0.6514,
  "Peyton Watson": 0.6226,
  "Precious Achiuwa": 0.6726,
  "Quentin Grimes": 0.6312,
  "Quenton Jackson": 0.7353,
  "Quinten Post": 0.6494,
  "RJ Barrett": 0.5472,
  "RayJ Dennis": 1.0,
  "Rayan Rupert": 0.8113,
  "Reece Beekman": 0.8,
  "Reed Sheppard": 0.624,
  "Richaun Holmes": 0.7692,
  "Ricky Council IV": 0.6618,
  "Rob Dillingham": 0.6863,
  "Robert Williams III": 1.0,
  "Ronald Holland II": 0.6447,
  "Royce O'Neale": 0.6395,
  "Rudy Gobert": 0.6224,
  "Rui Hachimura": 0.7105,
  "Russell Westbrook": 0.6493,
  "Ryan Dunn": 0.62,
  "Ryan Kalkbrenner": 0.5893,
  "Ryan Nembhard": 0.9091,
  "Ryan Rollins": 0.6529,
  "Saddiq Bey": 0.625,
  "Sam Hauser": 0.5957,
  "Sam Merrill": 0.6106,
  "Sandro Mamukelashvili": 0.648,
  "Santi Aldama": 0.5842,
  "Scoot Henderson": 0.6517,
  "Scottie Barnes": 0.6571,
  "Scotty Pippen Jr.": 0.5811,
  "Seth Curry": 0.7097,
  "Shaedon Sharpe": 0.687,
  "Shai Gilgeous-Alexander": 0.5652,
  "Shake Milton": 0.6346,
  "Sidy Cissoko": 0.7143,
  "Simone Fontecchio": 0.67,
  "Sion James": 0.6792,
  "Spencer Dinwiddie": 0.5811,
  "Spencer Jones": 0.7778,
  "Stanley Umude": 1.0,
  "Stephen Curry": 0.6415,
  "Stephon Castle": 0.5634,
  "Steven Adams": 0.6154,
  "Svi Mykhailiuk": 0.6857,
  "T.J. McConnell": 0.5391,
  "Taj Gibson": 0.8438,
  "Talen Horton-Tucker": 0.6604,
  "Tari Eason": 0.7339,
  "Taurean Prince": 0.6897,
  "Taylor Hendricks": 0.7143,
  "Terance Mann": 0.6964,
  "Terrence Shannon Jr.": 0.8125,
  "Terry Rozier": 0.7119,
  "Thomas Bryant": 0.6765,
  "Tidjane Sala\u00fcn": 0.5636,
  "Tim Hardaway Jr.": 0.6389,
  "Tobias Harris": 0.6336,
  "Tony Bradley": 0.5,
  "Torrey Craig": 0.6667,
  "Tosan Evbuomwan": 0.6957,
  "Toumani Camara": 0.5833,
  "Trae Young": 0.6824,
  "Trayce Jackson-Davis": 0.7018,
  "Tre Johnson": 0.6667,
  "Tre Jones": 0.67,
  "Tre Mann": 0.75,
  "Trendon Watford": 0.6557,
  "Trevelin Queen": 0.72,
  "Trey Alexander": 0.8889,
  "Trey Jemison III": 0.697,
  "Trey Lyles": 0.6719,
  "Trey Murphy III": 0.6372,
  "Tristan Thompson": 0.8571,
  "Tristan Vukcevic": 0.6829,
  "Tristan da Silva": 0.6204,
  "Ty Jerome": 0.5696,
  "TyTy Washington Jr.": 0.8182,
  "Tyler Herro": 0.5755,
  "Tyler Kolek": 0.8,
  "Tyler Smith": 0.6667,
  "Tyrese Haliburton": 0.5882,
  "Tyrese Martin": 0.7237,
  "Tyrese Maxey": 0.5763,
  "Tyus Jones": 0.5644,
  "VJ Edgecombe": 0.5915,
  "Vasilije Micic": 0.7222,
  "Victor Wembanyama": 0.5619,
  "Vince Williams Jr.": 0.6818,
  "V\u00edt Krej\u010d\u00ed": 0.8077,
  "Walker Kessler": 0.6379,
  "Walter Clayton Jr.": 0.6333,
  "Wendell Carter Jr.": 0.6349,
  "Wendell Moore Jr.": 0.6129,
  "Will Richard": 0.6842,
  "Will Riley": 0.7941,
  "Xavier Tillman": 0.963,
  "Yuki Kawamura": 0.875,
  "Yves Missi": 0.5306,
  "Zaccharie Risacher": 0.6875,
  "Zach Collins": 0.697,
  "Zach Edey": 0.7083,
  "Zach LaVine": 0.6111,
  "Zeke Nnaji": 0.7895,
  "Ziaire Williams": 0.6737,
  "Zion Williamson": 0.686
}